datasette_external_links_new_tabs/__init__.py
datasette_external_links_new_tabs-0.1.dist-info/LICENSE
datasette_external_links_new_tabs-0.1.dist-info/METADATA
datasette_external_links_new_tabs-0.1.dist-info/WHEEL
datasette_external_links_new_tabs-0.1.dist-info/entry_points.txt
datasette_external_links_new_tabs-0.1.dist-info/top_level.txt
datasette_external_links_new_tabs-0.1.dist-info/RECORD
