Metadata-Version: 2.1
Name: datasette-external-links-new-tabs
Version: 0.1
Summary: Datasette plugin to open external links in new tabs
Home-page: https://github.com/ocdtrekkie/datasette-external-links-new-tabs
Author: Jacob Weisz
License: Apache License, Version 2.0
Project-URL: Issues, https://github.com/ocdtrekkie/datasette-external-links-new-tabs/issues
Project-URL: CI, https://github.com/ocdtrekkie/datasette-external-links-new-tabs/actions
Project-URL: Changelog, https://github.com/ocdtrekkie/datasette-external-links-new-tabs/releases
Classifier: Framework :: Datasette
Classifier: License :: OSI Approved :: Apache Software License
Requires-Python: >=3.7
License-File: LICENSE
Requires-Dist: datasette
Provides-Extra: test
Requires-Dist: pytest ; extra == 'test'
Requires-Dist: pytest-asyncio ; extra == 'test'
